oci_httpx_auth/__init__.py
oci_httpx_auth/_auth.py
oci_httpx_auth/_generated/__init__.py
oci_httpx_auth/_generated/_region.py
oci_httpx_auth/_generated/_service.py
oci_httpx_auth/_generated/_service_endpoint_templates.py
oci_httpx_auth/_generated/_service_specs.py
oci_httpx_auth/_retrier.py
oci_httpx_auth/_signer.py
oci_httpx_auth/_util.py
oci_httpx_auth/py.typed
oci_httpx_auth-0.11.0.dist-info/WHEEL
oci_httpx_auth-0.11.0.dist-info/METADATA
oci_httpx_auth-0.11.0.dist-info/RECORD
