Metadata-Version: 2.3
Name: oci-httpx-auth
Version: 0.11.0
Summary: Add your description here
Author: Florian Daude
Author-email: Florian Daude <floriandaude@hotmail.fr>
Requires-Dist: cryptography>=46.0.3
Requires-Dist: httpx>=0.28.1
Requires-Dist: pydantic>=2.12.4
Requires-Python: >=3.12
